[
  {
    "user_id": 455993452,
    "user_login": "sharonqueen",
    "user_display_name": "SharonQueen",
    "user_broadcaster_type": "partner",
    "user_profile_image_url": "https://static-cdn.jtvnw.net/jtv_user_pictures/f1cf4264-36f8-44f6-864e-bc82081da739-profile_image-300x300.png",
    "user_offline_image_url": "https://static-cdn.jtvnw.net/jtv_user_pictures/414785ad-7ce5-40a3-9621-138181a60245-channel_offline_image-1920x1080.jpeg",
    "stream_id": 46086963229,
    "stream_game_id": "509659",
    "stream_game_name": "ASMR",
    "stream_title": "Senpai 18+⚠️🔴👋  !web !king !tiktok  !newvid ( !youtube !gifters !topDono ) #anime #uwu #cosplay #senpai",
    "stream_viewer_count": 996,
    "stream_thumbnail_url": "https://static-cdn.jtvnw.net/previews-ttv/live_user_sharonqueen-{width}x{height}.jpg"
  },
  {
    "user_id": 475566892,
    "user_login": "shyphoebe",
    "user_display_name": "shyphoebe",
    "user_broadcaster_type": "affiliate",
    "user_profile_image_url": "https://static-cdn.jtvnw.net/jtv_user_pictures/01104eb3-0fea-4889-842e-1b43c4f97f36-profile_image-300x300.png",
    "user_offline_image_url": "https://static-cdn.jtvnw.net/jtv_user_pictures/31333dd3-75e3-49f1-9df2-a04b8484df31-channel_offline_image-1920x1080.png",
    "stream_id": 45149661212,
    "stream_game_id": "509659",
    "stream_game_name": "ASMR",
    "stream_title": "❤️ SWEET EAR LICKING ASMR AND EYE CONTACT ❤️ !s !rr",
    "stream_viewer_count": 191,
    "stream_thumbnail_url": "https://static-cdn.jtvnw.net/previews-ttv/live_user_shyphoebe-{width}x{height}.jpg"
  },
  {
    "user_id": 161737008,
    "user_login": "kyootbot",
    "user_display_name": "kyootbot",
    "user_broadcaster_type": "partner",
    "user_profile_image_url": "https://static-cdn.jtvnw.net/jtv_user_pictures/21d3db3d-4dab-445c-92f7-b0bf474076c6-profile_image-300x300.png",
    "user_offline_image_url": "https://static-cdn.jtvnw.net/jtv_user_pictures/f9029db2-3ecf-4ac4-968c-54e6de4cee80-channel_offline_image-1920x1080.png",
    "stream_id": 46095875213,
    "stream_game_id": "509658",
    "stream_game_name": "Just Chatting",
    "stream_title": "♥ SPEED DATING VIEWERS ♥ | ♥ NOT IMPRESSED = KICK ♥ | ♥ dont be offended LOL ♥ | CHAT WILL RATE YOU! | !join ♥ !merch ♥ 3080 !giveaway",
    "stream_viewer_count": 43,
    "stream_thumbnail_url": "https://static-cdn.jtvnw.net/previews-ttv/live_user_kyootbot-{width}x{height}.jpg"
  },
  {
    "user_id": 184147110,
    "user_login": "olesyaliberman",
    "user_display_name": "OLESYALIBERMAN",
    "user_broadcaster_type": "partner",
    "user_profile_image_url": "https://static-cdn.jtvnw.net/jtv_user_pictures/42e81376-ba6a-407e-bfa2-34323b3bb808-profile_image-300x300.jpeg",
    "user_offline_image_url": "https://static-cdn.jtvnw.net/jtv_user_pictures/8daf5e24-cc88-422f-b405-75fdaa480418-channel_offline_image-1920x1080.jpeg",
    "stream_id": 45164643612,
    "stream_game_id": "509658",
    "stream_game_name": "Just Chatting",
    "stream_title": "18+ !phub !donate BIRTHDAY SHEESH 🍑 3$ - NAME ON BOARD | SQUATS EVERY 20$ | only donations are available",
    "stream_viewer_count": 23,
    "stream_thumbnail_url": "https://static-cdn.jtvnw.net/previews-ttv/live_user_olesyaliberman-{width}x{height}.jpg"
  },
  {
    "user_id": 434734417,
    "user_login": "allecakes",
    "user_display_name": "allecakes",
    "user_broadcaster_type": "partner",
    "user_profile_image_url": "https://static-cdn.jtvnw.net/jtv_user_pictures/3280ac85-6f7a-427f-9ed7-2f9bc82541f7-profile_image-300x300.png",
    "user_offline_image_url": "https://static-cdn.jtvnw.net/jtv_user_pictures/095ae1c9-a571-489d-b347-4f524f54d99c-channel_offline_image-1920x1080.jpeg",
    "stream_id": 40695634347,
    "stream_game_id": "509658",
    "stream_game_name": "Just Chatting",
    "stream_title": "BOOTY <3 WORKOUT WEDNESDAY!! || !socials",
    "stream_viewer_count": 14,
    "stream_thumbnail_url": "https://static-cdn.jtvnw.net/previews-ttv/live_user_allecakes-{width}x{height}.jpg"
  },
  {
    "user_id": 178570113,
    "user_login": "spookyunagi",
    "user_display_name": "SpookyUnagi",
    "user_broadcaster_type": "partner",
    "user_profile_image_url": "https://static-cdn.jtvnw.net/jtv_user_pictures/7bad214c-75a9-458c-a365-ead07bf861a9-profile_image-300x300.png",
    "user_offline_image_url": "https://static-cdn.jtvnw.net/jtv_user_pictures/d29416db-6518-467b-9e29-4ae0dca9a066-channel_offline_image-1920x1080.jpeg",
    "stream_id": 46093986925,
    "stream_game_id": "116747788",
    "stream_game_name": "Pools, Hot Tubs, and Beaches",
    "stream_title": "*metal horns* // NEW TikTok !t !s",
    "stream_viewer_count": 10,
    "stream_thumbnail_url": "https://static-cdn.jtvnw.net/previews-ttv/live_user_spookyunagi-{width}x{height}.jpg"
  },
  {
    "user_id": 280116605,
    "user_login": "kayleerosevera",
    "user_display_name": "KayleeRoseVera",
    "user_broadcaster_type": "affiliate",
    "user_profile_image_url": "https://static-cdn.jtvnw.net/jtv_user_pictures/1edbcaa9-1fe9-471a-baef-afb457826899-profile_image-300x300.png",
    "user_offline_image_url": "https://static-cdn.jtvnw.net/jtv_user_pictures/6137a344-e8dc-430e-898d-ea37f0679a6f-channel_offline_image-1920x1080.jpeg",
    "stream_id": 46094875549,
    "stream_game_id": "509658",
    "stream_game_name": "Just Chatting",
    "stream_title": "(｡◕ ‿ ◕｡) !hellofresh !socials !snap !donate",
    "stream_viewer_count": 3,
    "stream_thumbnail_url": "https://static-cdn.jtvnw.net/previews-ttv/live_user_kayleerosevera-{width}x{height}.jpg"
  },
  {
    "user_id": 504299521,
    "user_login": "pinkfloweremoji",
    "user_display_name": "PinkFlowerEmoji",
    "user_broadcaster_type": "affiliate",
    "user_profile_image_url": "https://static-cdn.jtvnw.net/jtv_user_pictures/2c88d8c2-0335-4052-af07-232e093b9a0b-profile_image-300x300.png",
    "user_offline_image_url": "",
    "stream_id": 46095267677,
    "stream_game_id": "509658",
    "stream_game_name": "Just Chatting",
    "stream_title": "❤️‍🔥 hiiiii  chill yoga vibes & twister?! <3  !merch !youtube   ❤️‍🔥  🦋!socials",
    "stream_viewer_count": 0,
    "stream_thumbnail_url": "https://static-cdn.jtvnw.net/previews-ttv/live_user_pinkfloweremoji-{width}x{height}.jpg"
  },
  {
    "user_id": 486289378,
    "user_login": "peachling",
    "user_display_name": "Peachling",
    "user_broadcaster_type": "partner",
    "user_profile_image_url": "https://static-cdn.jtvnw.net/jtv_user_pictures/080cd356-1589-4b2a-b731-25666b86de0a-profile_image-300x300.png",
    "user_offline_image_url": "https://static-cdn.jtvnw.net/jtv_user_pictures/24060a30-6ada-4bed-a06b-398820fd7555-channel_offline_image-1920x1080.png",
    "stream_id": 39636642457,
    "stream_game_id": "509658",
    "stream_game_name": "Just Chatting",
    "stream_title": "😮 VIEWER CONFESSIONS 😮 !submit !gfuel !socials",
    "stream_viewer_count": 0,
    "stream_thumbnail_url": "https://static-cdn.jtvnw.net/previews-ttv/live_user_peachling-{width}x{height}.jpg"
  },
  {
    "user_id": 173319589,
    "user_login": "jjolbi1987",
    "user_display_name": "쫄비",
    "user_broadcaster_type": "partner",
    "user_profile_image_url": "https://static-cdn.jtvnw.net/jtv_user_pictures/fabb58ae-01a9-49f1-91f2-80589adb450d-profile_image-300x300.jpg",
    "user_offline_image_url": "https://static-cdn.jtvnw.net/jtv_user_pictures/4799813c-35f1-4605-b8f3-fa41412a0320-channel_offline_image-1920x1080.jpeg",
    "stream_id": 46094535677,
    "stream_game_id": "509658",
    "stream_game_name": "Just Chatting",
    "stream_title": "니가몰알아! 🎀 !메뉴 20220407",
    "stream_viewer_count": 0,
    "stream_thumbnail_url": "https://static-cdn.jtvnw.net/previews-ttv/live_user_jjolbi1987-{width}x{height}.jpg"
  },
  {
    "user_id": 148114007,
    "user_login": "rayrachel",
    "user_display_name": "RayRachel",
    "user_broadcaster_type": "partner",
    "user_profile_image_url": "https://static-cdn.jtvnw.net/jtv_user_pictures/628357ab-ea60-428d-a106-903cbffa937e-profile_image-300x300.png",
    "user_offline_image_url": "https://static-cdn.jtvnw.net/jtv_user_pictures/a942ea9f-f524-4904-80f5-0dee5e339446-channel_offline_image-1920x1080.jpeg",
    "stream_id": 39636591769,
    "stream_game_id": "509658",
    "stream_game_name": "Just Chatting",
    "stream_title": "Lets get some W's | !social !discord #AD",
    "stream_viewer_count": 0,
    "stream_thumbnail_url": "https://static-cdn.jtvnw.net/previews-ttv/live_user_rayrachel-{width}x{height}.jpg"
  },
  {
    "user_id": 64138868,
    "user_login": "tymwits",
    "user_display_name": "tymwits",
    "user_broadcaster_type": "partner",
    "user_profile_image_url": "https://static-cdn.jtvnw.net/jtv_user_pictures/35505d22-5ba7-4a58-897e-717f4a961f85-profile_image-300x300.png",
    "user_offline_image_url": "https://static-cdn.jtvnw.net/jtv_user_pictures/c6caa31f-f338-4316-802f-8056d01bf123-channel_offline_image-1920x1080.jpeg",
    "stream_id": 39636449353,
    "stream_game_id": "509658",
    "stream_game_name": "Just Chatting",
    "stream_title": "*bops*  !s = 🔥 socials",
    "stream_viewer_count": 0,
    "stream_thumbnail_url": "https://static-cdn.jtvnw.net/previews-ttv/live_user_tymwits-{width}x{height}.jpg"
  },
  {
    "user_id": 155874595,
    "user_login": "elisabetetv",
    "user_display_name": "ElisabeteTV",
    "user_broadcaster_type": "partner",
    "user_profile_image_url": "https://static-cdn.jtvnw.net/jtv_user_pictures/87ad6bec-1bfb-4ffe-9bf5-a5b4d1a1ec48-profile_image-300x300.png",
    "user_offline_image_url": "https://static-cdn.jtvnw.net/jtv_user_pictures/eee20302-39f9-4897-bbed-c58f373cf84b-channel_offline_image-1920x1080.jpeg",
    "stream_id": 45163541180,
    "stream_game_id": "509659",
    "stream_game_name": "ASMR",
    "stream_title": "ASMR EAR LICK 💜 I LOVE YOU 💦💋 !SOCIALS !PRIME !SUB",
    "stream_viewer_count": 0,
    "stream_thumbnail_url": "https://static-cdn.jtvnw.net/previews-ttv/live_user_elisabetetv-{width}x{height}.jpg"
  },
  {
    "user_id": 237238176,
    "user_login": "seolyihyeon",
    "user_display_name": "설이현",
    "user_broadcaster_type": "partner",
    "user_profile_image_url": "https://static-cdn.jtvnw.net/jtv_user_pictures/c5500685-1002-487c-a6c2-5d54668d7063-profile_image-300x300.png",
    "user_offline_image_url": "https://static-cdn.jtvnw.net/jtv_user_pictures/edbd2b5a-de9d-4429-bb1b-a478a7af66fb-channel_offline_image-1920x1080.png",
    "stream_id": 46093431517,
    "stream_game_id": "509658",
    "stream_game_name": "Just Chatting",
    "stream_title": "❄️ 3일째 강제기상",
    "stream_viewer_count": 0,
    "stream_thumbnail_url": "https://static-cdn.jtvnw.net/previews-ttv/live_user_seolyihyeon-{width}x{height}.jpg"
  },
  {
    "user_id": 625405963,
    "user_login": "elena_fn",
    "user_display_name": "elena_fn",
    "user_broadcaster_type": "affiliate",
    "user_profile_image_url": "https://static-cdn.jtvnw.net/jtv_user_pictures/2ea103ae-8c15-4a22-9528-9f56dcfd06eb-profile_image-300x300.png",
    "user_offline_image_url": "",
    "stream_id": 45162787596,
    "stream_game_id": "509659",
    "stream_game_name": "ASMR",
    "stream_title": "NO TALK ASMR  EARLICKING! ❤️ | !social ❤️ITA/SPA/ENG",
    "stream_viewer_count": 0,
    "stream_thumbnail_url": "https://static-cdn.jtvnw.net/previews-ttv/live_user_elena_fn-{width}x{height}.jpg"
  },
  {
    "user_id": 152762898,
    "user_login": "kristinadaniellexo",
    "user_display_name": "kristinadaniellexo",
    "user_broadcaster_type": "affiliate",
    "user_profile_image_url": "https://static-cdn.jtvnw.net/jtv_user_pictures/2b09ee29-cfc1-4aee-bda3-23b6c462dfbe-profile_image-300x300.png",
    "user_offline_image_url": "",
    "stream_id": 46091710301,
    "stream_game_id": "509659",
    "stream_game_name": "ASMR",
    "stream_title": "😈🔴18+ HOTTEST licks on twitch 💦 !socials !yt !rr",
    "stream_viewer_count": 0,
    "stream_thumbnail_url": "https://static-cdn.jtvnw.net/previews-ttv/live_user_kristinadaniellexo-{width}x{height}.jpg"
  },
  {
    "user_id": 93517122,
    "user_login": "crystal",
    "user_display_name": "Crystal",
    "user_broadcaster_type": "partner",
    "user_profile_image_url": "https://static-cdn.jtvnw.net/jtv_user_pictures/dd137693-e8af-43df-a0fa-7824f486c6f5-profile_image-300x300.png",
    "user_offline_image_url": "https://static-cdn.jtvnw.net/jtv_user_pictures/3ad7c628-aea9-403d-b25b-3cf436128478-channel_offline_image-1920x1080.png",
    "stream_id": 46091442829,
    "stream_game_id": "509659",
    "stream_game_name": "ASMR",
    "stream_title": "❤️👅💦 LIVE ASMR LICKS & TINGLES ❤️👅💦 !S for all my links !sub !prime",
    "stream_viewer_count": 0,
    "stream_thumbnail_url": "https://static-cdn.jtvnw.net/previews-ttv/live_user_crystal-{width}x{height}.jpg"
  }
]
