[
  {
    "user_id": 562723403,
    "user_login": "strawberrytabby",
    "user_display_name": "strawberrytabby",
    "user_broadcaster_type": "partner",
    "user_profile_image_url": "https://static-cdn.jtvnw.net/jtv_user_pictures/68e692b3-a397-4608-bb07-decaee9d45bf-profile_image-300x300.png",
    "user_offline_image_url": "https://static-cdn.jtvnw.net/jtv_user_pictures/91ab9cee-4e48-4793-9a46-ca0775a5fe13-channel_offline_image-1920x1080.jpeg",
    "stream_id": 41038466648,
    "stream_game_id": "509658",
    "stream_game_name": "Just Chatting",
    "stream_title": "ðŸŒ€ SURVIVING HURRICANE IDALIA! ðŸŒ€| !socials ðŸŒ¶ï¸",
    "stream_viewer_count": 2013,
    "stream_thumbnail_url": "https://static-cdn.jtvnw.net/previews-ttv/live_user_strawberrytabby-{width}x{height}.jpg"
  },
  {
    "user_id": 503369631,
    "user_login": "asianbunnyx",
    "user_display_name": "asianbunnyx",
    "user_broadcaster_type": "partner",
    "user_profile_image_url": "https://static-cdn.jtvnw.net/jtv_user_pictures/2647e980-bb05-4049-908e-d217eb7235ea-profile_image-300x300.png",
    "user_offline_image_url": "",
    "stream_id": 41038437784,
    "stream_game_id": "509658",
    "stream_game_name": "Just Chatting",
    "stream_title": "(18+)NEURON ACTIVATIONS, SEROTONIN BOOST !discord !socials",
    "stream_viewer_count": 1191,
    "stream_thumbnail_url": "https://static-cdn.jtvnw.net/previews-ttv/live_user_asianbunnyx-{width}x{height}.jpg"
  },
  {
    "user_id": 184147110,
    "user_login": "olesyaliberman",
    "user_display_name": "OLESYALIBERMAN",
    "user_broadcaster_type": "partner",
    "user_profile_image_url": "https://static-cdn.jtvnw.net/jtv_user_pictures/f73f547c-913d-4565-bde4-3b89d0040745-profile_image-300x300.png",
    "user_offline_image_url": "https://static-cdn.jtvnw.net/jtv_user_pictures/8daf5e24-cc88-422f-b405-75fdaa480418-channel_offline_image-1920x1080.jpeg",
    "stream_id": 40570668359,
    "stream_game_id": "509658",
    "stream_game_name": "Just Chatting",
    "stream_title": "!phub !tt ðŸ’— stretching with stepsis ðŸ’— !size",
    "stream_viewer_count": 918,
    "stream_thumbnail_url": "https://static-cdn.jtvnw.net/previews-ttv/live_user_olesyaliberman-{width}x{height}.jpg"
  },
  {
    "user_id": 197406569,
    "user_login": "thenicolet",
    "user_display_name": "TheNicoleT",
    "user_broadcaster_type": "partner",
    "user_profile_image_url": "https://static-cdn.jtvnw.net/jtv_user_pictures/d9995fd9-ff5b-46f4-8722-809fbe77798f-profile_image-300x300.png",
    "user_offline_image_url": "https://static-cdn.jtvnw.net/jtv_user_pictures/b1802330-bc9f-43b4-8ce4-1c37d170236b-channel_offline_image-1920x1080.png",
    "stream_id": 42672438731,
    "stream_game_id": "509658",
    "stream_game_name": "Just Chatting",
    "stream_title": "Cooking STEAK  then bikini & ASMR !socials",
    "stream_viewer_count": 651,
    "stream_thumbnail_url": "https://static-cdn.jtvnw.net/previews-ttv/live_user_thenicolet-{width}x{height}.jpg"
  },
  {
    "user_id": 536906710,
    "user_login": "ijenz",
    "user_display_name": "IJenz",
    "user_broadcaster_type": "partner",
    "user_profile_image_url": "https://static-cdn.jtvnw.net/jtv_user_pictures/1b932a44-257f-46ae-aa49-bfe037671067-profile_image-300x300.png",
    "user_offline_image_url": "https://static-cdn.jtvnw.net/jtv_user_pictures/3668b504-8985-4352-9afd-c016c8c49e97-channel_offline_image-1920x1080.png",
    "stream_id": 39903323397,
    "stream_game_id": "509659",
    "stream_game_name": "ASMR",
    "stream_title": "!RR ASMR COSPLAY MILITAR ðŸ§¸ðŸ¥° @ijenz",
    "stream_viewer_count": 522,
    "stream_thumbnail_url": "https://static-cdn.jtvnw.net/previews-ttv/live_user_ijenz-{width}x{height}.jpg"
  },
  {
    "user_id": 500906914,
    "user_login": "sandraskins",
    "user_display_name": "SandraSkins",
    "user_broadcaster_type": "partner",
    "user_profile_image_url": "https://static-cdn.jtvnw.net/jtv_user_pictures/a16b82f7-78c7-4ea9-9203-703f2f50dfcf-profile_image-300x300.png",
    "user_offline_image_url": "https://static-cdn.jtvnw.net/jtv_user_pictures/6de01593-05a6-4627-a6b4-d5ffa1ce1e86-channel_offline_image-1920x1080.png",
    "stream_id": 41799183561,
    "stream_game_id": "27471",
    "stream_game_name": "Minecraft",
    "stream_title": "DEDSAFIO DIA 2 CON UN TRY HARD EN MI TEAM :o Â¿GANAREMOS?",
    "stream_viewer_count": 515,
    "stream_thumbnail_url": "https://static-cdn.jtvnw.net/previews-ttv/live_user_sandraskins-{width}x{height}.jpg"
  },
  {
    "user_id": 452985358,
    "user_login": "foxenkin",
    "user_display_name": "FoxenKin",
    "user_broadcaster_type": "partner",
    "user_profile_image_url": "https://static-cdn.jtvnw.net/jtv_user_pictures/3a4e7871-9fe2-40be-b040-8edf32a2818c-profile_image-300x300.png",
    "user_offline_image_url": "https://static-cdn.jtvnw.net/jtv_user_pictures/561d6052-b99c-4961-aeac-f1dcc49ac4fc-channel_offline_image-1920x1080.png",
    "stream_id": 49194107357,
    "stream_game_id": "509659",
    "stream_game_name": "ASMR",
    "stream_title": "RERUN  â¤  TINGLES  â¤  TINGLES  â¤  TINGLES  â¤  !S for Links ðŸ‘… â¤ ï¸ | EN + FR | New Video !YT",
    "stream_viewer_count": 483,
    "stream_thumbnail_url": "https://static-cdn.jtvnw.net/previews-ttv/live_user_foxenkin-{width}x{height}.jpg"
  },
  {
    "user_id": 195465496,
    "user_login": "loraveee",
    "user_display_name": "Loraveee",
    "user_broadcaster_type": "partner",
    "user_profile_image_url": "https://static-cdn.jtvnw.net/jtv_user_pictures/ac819358-0fd2-47b8-b1e2-c7adf7068cba-profile_image-300x300.png",
    "user_offline_image_url": "",
    "stream_id": 42671914251,
    "stream_game_id": "509658",
    "stream_game_name": "Just Chatting",
    "stream_title": "WORK OUT STREAM -- Pool Later Possibly ðŸ‘ðŸ’‹- !NEW !SOCIALS",
    "stream_viewer_count": 435,
    "stream_thumbnail_url": "https://static-cdn.jtvnw.net/previews-ttv/live_user_loraveee-{width}x{height}.jpg"
  },
  {
    "user_id": 455993452,
    "user_login": "sharonqueen",
    "user_display_name": "SharonQueen",
    "user_broadcaster_type": "partner",
    "user_profile_image_url": "https://static-cdn.jtvnw.net/jtv_user_pictures/2fa82a48-74bd-4428-a89e-fcd27b549e1a-profile_image-300x300.png",
    "user_offline_image_url": "https://static-cdn.jtvnw.net/jtv_user_pictures/414785ad-7ce5-40a3-9621-138181a60245-channel_offline_image-1920x1080.jpeg",
    "stream_id": 39903955717,
    "stream_game_id": "509659",
    "stream_game_name": "ASMR",
    "stream_title": "â™¡ UwU â›”18+ðŸ”žðŸ”´ðŸ‘‹ !S  !king  !gifters  !biters  ASMR @SharonQueen #anime #uwu #cosplay #senpai -rerun",
    "stream_viewer_count": 371,
    "stream_thumbnail_url": "https://static-cdn.jtvnw.net/previews-ttv/live_user_sharonqueen-{width}x{height}.jpg"
  },
  {
    "user_id": 67181956,
    "user_login": "theoneandonlydragon",
    "user_display_name": "TheOneAndOnlyDragon",
    "user_broadcaster_type": "partner",
    "user_profile_image_url": "https://static-cdn.jtvnw.net/jtv_user_pictures/3fb73fca-47d2-42df-8f52-14d4bbef03c0-profile_image-300x300.png",
    "user_offline_image_url": "https://static-cdn.jtvnw.net/jtv_user_pictures/f607af0b-6581-4d45-9bf9-bd825d179be4-channel_offline_image-1920x1080.png",
    "stream_id": 42671875051,
    "stream_game_id": "116747788",
    "stream_game_name": "Pools, Hot Tubs, and Beaches",
    "stream_title": "GOIN' UP on a TUESDAYâ˜€ï¸ TYPE !D ðŸ’¦!SOCIALSðŸ’¦",
    "stream_viewer_count": 225,
    "stream_thumbnail_url": "https://static-cdn.jtvnw.net/previews-ttv/live_user_theoneandonlydragon-{width}x{height}.jpg"
  },
  {
    "user_id": 753374792,
    "user_login": "sarenewild",
    "user_display_name": "SareneWild",
    "user_broadcaster_type": "partner",
    "user_profile_image_url": "https://static-cdn.jtvnw.net/jtv_user_pictures/08ae24a4-f86b-4fff-8687-5bd820dca03f-profile_image-300x300.png",
    "user_offline_image_url": "https://static-cdn.jtvnw.net/jtv_user_pictures/a0c5d65e-745a-461a-9723-3e0d80eac8ef-channel_offline_image-1920x1080.png",
    "stream_id": 42670104411,
    "stream_game_id": "509659",
    "stream_game_name": "ASMR",
    "stream_title": "ðŸŽ§ ð“ð“¢ð“œð“¡ !ð“¡ð“¡ ðŸ’¤ ð—¡ð—¼ ð—§ð—®ð—¹ð—¸ð—¶ð—»ð—´ | ðŸ‘… Gentle Mouth Sounds ðŸ’¦ 3ð‘«ð’Šð’ ð‘©ð’Šð’ð’‚ð’–ð’“ð’‚ð’ | ðŸ’“LIVE ON:Mon/Tue/Thur 8amPDT | !LINKTREE",
    "stream_viewer_count": 225,
    "stream_thumbnail_url": "https://static-cdn.jtvnw.net/previews-ttv/live_user_sarenewild-{width}x{height}.jpg"
  },
  {
    "user_id": 715774157,
    "user_login": "mstriggahappy_",
    "user_display_name": "MsTriggaHappy_",
    "user_broadcaster_type": "affiliate",
    "user_profile_image_url": "https://static-cdn.jtvnw.net/jtv_user_pictures/54ce3310-fe77-43bd-b5ec-b33a01462de8-profile_image-300x300.png",
    "user_offline_image_url": "",
    "stream_id": 49195778685,
    "stream_game_id": "32982",
    "stream_game_name": "Grand Theft Auto V",
    "stream_title": "E-GIRL CITY | Roulette RP",
    "stream_viewer_count": 183,
    "stream_thumbnail_url": "https://static-cdn.jtvnw.net/previews-ttv/live_user_mstriggahappy_-{width}x{height}.jpg"
  },
  {
    "user_id": 250350524,
    "user_login": "hottea",
    "user_display_name": "HotTea",
    "user_broadcaster_type": "partner",
    "user_profile_image_url": "https://static-cdn.jtvnw.net/jtv_user_pictures/56b94488-6315-4c02-a2fa-246d02237c2a-profile_image-300x300.png",
    "user_offline_image_url": "",
    "stream_id": 41038342088,
    "stream_game_id": "509658",
    "stream_game_name": "Just Chatting",
    "stream_title": "TACO TUESDAY with TEA  !S !dono !swag !youtube",
    "stream_viewer_count": 119,
    "stream_thumbnail_url": "https://static-cdn.jtvnw.net/previews-ttv/live_user_hottea-{width}x{height}.jpg"
  },
  {
    "user_id": 148114007,
    "user_login": "rayrachel",
    "user_display_name": "RayRachel",
    "user_broadcaster_type": "partner",
    "user_profile_image_url": "https://static-cdn.jtvnw.net/jtv_user_pictures/628357ab-ea60-428d-a106-903cbffa937e-profile_image-300x300.png",
    "user_offline_image_url": "https://static-cdn.jtvnw.net/jtv_user_pictures/a942ea9f-f524-4904-80f5-0dee5e339446-channel_offline_image-1920x1080.jpeg",
    "stream_id": 42671606923,
    "stream_game_id": "509658",
    "stream_game_name": "Just Chatting",
    "stream_title": "Paint me !socials",
    "stream_viewer_count": 115,
    "stream_thumbnail_url": "https://static-cdn.jtvnw.net/previews-ttv/live_user_rayrachel-{width}x{height}.jpg"
  },
  {
    "user_id": 89791124,
    "user_login": "leah_ayame",
    "user_display_name": "Leah_Ayame",
    "user_broadcaster_type": "partner",
    "user_profile_image_url": "https://static-cdn.jtvnw.net/jtv_user_pictures/81b2b075-856c-47d3-ba44-f8a1d11ce631-profile_image-300x300.png",
    "user_offline_image_url": "",
    "stream_id": 49195878797,
    "stream_game_id": "509658",
    "stream_game_name": "Just Chatting",
    "stream_title": "Drinks and Truths >.> !socials !discord !hellofresh !wishlist",
    "stream_viewer_count": 109,
    "stream_thumbnail_url": "https://static-cdn.jtvnw.net/previews-ttv/live_user_leah_ayame-{width}x{height}.jpg"
  },
  {
    "user_id": 429614703,
    "user_login": "rhinospiritx",
    "user_display_name": "RhinoSpiritX",
    "user_broadcaster_type": "partner",
    "user_profile_image_url": "https://static-cdn.jtvnw.net/jtv_user_pictures/6d8927a8-7c75-43b9-9a60-31f4295d1777-profile_image-300x300.jpeg",
    "user_offline_image_url": "https://static-cdn.jtvnw.net/jtv_user_pictures/6c9f6efa-a298-4fcb-b07a-eb19e4723c12-channel_offline_image-1920x1080.png",
    "stream_id": 41037199768,
    "stream_game_id": "116747788",
    "stream_game_name": "Pools, Hot Tubs, and Beaches",
    "stream_title": "18+ Bikini Pool Party ðŸ’œ rerun ðŸŒ¸IG: RhinoSpiritXASMR",
    "stream_viewer_count": 78,
    "stream_thumbnail_url": "https://static-cdn.jtvnw.net/previews-ttv/live_user_rhinospiritx-{width}x{height}.jpg"
  },
  {
    "user_id": 74707525,
    "user_login": "denver_maxx",
    "user_display_name": "denver_maxx",
    "user_broadcaster_type": "partner",
    "user_profile_image_url": "https://static-cdn.jtvnw.net/jtv_user_pictures/454e81af-4b2b-4381-ba69-c74dc0a7d3a9-profile_image-300x300.png",
    "user_offline_image_url": "https://static-cdn.jtvnw.net/jtv_user_pictures/9b0d5b60-a4e7-4d5d-9d6b-be602156aa0b-channel_offline_image-1920x1080.jpeg",
    "stream_id": 41799472985,
    "stream_game_id": "509658",
    "stream_game_name": "Just Chatting",
    "stream_title": "Tuesday Shenanigans <3 ~ !donate ~ !links ~",
    "stream_viewer_count": 67,
    "stream_thumbnail_url": "https://static-cdn.jtvnw.net/previews-ttv/live_user_denver_maxx-{width}x{height}.jpg"
  },
  {
    "user_id": 66438932,
    "user_login": "moxymary",
    "user_display_name": "MoxyMary",
    "user_broadcaster_type": "partner",
    "user_profile_image_url": "https://static-cdn.jtvnw.net/jtv_user_pictures/cee497cf-fffb-482e-8ec1-a4bfdf438210-profile_image-300x300.png",
    "user_offline_image_url": "https://static-cdn.jtvnw.net/jtv_user_pictures/3ad4d069-e2aa-42e5-b105-e13830e27d72-channel_offline_image-1920x1080.jpeg",
    "stream_id": 42671711019,
    "stream_game_id": "509658",
    "stream_game_name": "Just Chatting",
    "stream_title": "But could a depressed person do this?? â™¥ !links",
    "stream_viewer_count": 51,
    "stream_thumbnail_url": "https://static-cdn.jtvnw.net/previews-ttv/live_user_moxymary-{width}x{height}.jpg"
  },
  {
    "user_id": 280116605,
    "user_login": "kayleerosevera",
    "user_display_name": "KayleeRoseVera",
    "user_broadcaster_type": "affiliate",
    "user_profile_image_url": "https://static-cdn.jtvnw.net/jtv_user_pictures/571d6382-bf2c-4fef-9b1d-22ca3d584bf7-profile_image-300x300.png",
    "user_offline_image_url": "https://static-cdn.jtvnw.net/jtv_user_pictures/6137a344-e8dc-430e-898d-ea37f0679a6f-channel_offline_image-1920x1080.jpeg",
    "stream_id": 41800369817,
    "stream_game_id": "509658",
    "stream_game_name": "Just Chatting",
    "stream_title": "You deserve happiness ðŸ’—ðŸ’—ðŸ’—",
    "stream_viewer_count": 10,
    "stream_thumbnail_url": "https://static-cdn.jtvnw.net/previews-ttv/live_user_kayleerosevera-{width}x{height}.jpg"
  }
]
