[
  {
    "user_id": 61974931,
    "user_login": "leynainu",
    "user_display_name": "Leynainu",
    "user_broadcaster_type": "partner",
    "user_profile_image_url": "https://static-cdn.jtvnw.net/jtv_user_pictures/0971fcf6-c381-456a-848a-09889c20428a-profile_image-300x300.png",
    "user_offline_image_url": "https://static-cdn.jtvnw.net/jtv_user_pictures/c09dc972-31af-4b4b-8c94-15f4262343f1-channel_offline_image-1920x1080.jpeg",
    "stream_id": 44337171885,
    "stream_game_id": "509659",
    "stream_game_name": "ASMR",
    "stream_title": "💋Double D'io💋 / !social = all my Social Media",
    "stream_viewer_count": 2298,
    "stream_thumbnail_url": "https://static-cdn.jtvnw.net/previews-ttv/live_user_leynainu-{width}x{height}.jpg"
  },
  {
    "user_id": 469348555,
    "user_login": "taylor_jevaux",
    "user_display_name": "Taylor_Jevaux",
    "user_broadcaster_type": "partner",
    "user_profile_image_url": "https://static-cdn.jtvnw.net/jtv_user_pictures/6a571012-8dc4-41c2-a850-244a33e3b900-profile_image-300x300.png",
    "user_offline_image_url": "",
    "stream_id": 44334251341,
    "stream_game_id": "509659",
    "stream_game_name": "ASMR",
    "stream_title": "🔥FRENCH MAID EAR LICKING+ACCENT🔥 !socials ",
    "stream_viewer_count": 2000,
    "stream_thumbnail_url": "https://static-cdn.jtvnw.net/previews-ttv/live_user_taylor_jevaux-{width}x{height}.jpg"
  },
  {
    "user_id": 155874595,
    "user_login": "elisabetetv",
    "user_display_name": "ElisabeteTV",
    "user_broadcaster_type": "partner",
    "user_profile_image_url": "https://static-cdn.jtvnw.net/jtv_user_pictures/cae3ca63-510d-4715-b4ce-059dcf938978-profile_image-300x300.png",
    "user_offline_image_url": "https://static-cdn.jtvnw.net/jtv_user_pictures/eee20302-39f9-4897-bbed-c58f373cf84b-channel_offline_image-1920x1080.jpeg",
    "stream_id": 40186124091,
    "stream_game_id": "509659",
    "stream_game_name": "ASMR",
    "stream_title": "LIVE ASMR ❤️ POSITIVE VIBES ❤️ !PRIME !S ",
    "stream_viewer_count": 1485,
    "stream_thumbnail_url": "https://static-cdn.jtvnw.net/previews-ttv/live_user_elisabetetv-{width}x{height}.jpg"
  },
  {
    "user_id": 625405963,
    "user_login": "elena_fn",
    "user_display_name": "elena_fn",
    "user_broadcaster_type": "affiliate",
    "user_profile_image_url": "https://static-cdn.jtvnw.net/jtv_user_pictures/2ea103ae-8c15-4a22-9528-9f56dcfd06eb-profile_image-300x300.png",
    "user_offline_image_url": "",
    "stream_id": 43728847132,
    "stream_game_id": "509659",
    "stream_game_name": "ASMR",
    "stream_title": "❤️ ASMR EARLICKING  ENG /SPAIN/ITALIAN ❤️ | !sub !youtube !prime",
    "stream_viewer_count": 1200,
    "stream_thumbnail_url": "https://static-cdn.jtvnw.net/previews-ttv/live_user_elena_fn-{width}x{height}.jpg"
  },
  {
    "user_id": 576540233,
    "user_login": "seoahtv",
    "user_display_name": "seoahtv",
    "user_broadcaster_type": "partner",
    "user_profile_image_url": "https://static-cdn.jtvnw.net/jtv_user_pictures/ab8b314a-b74c-46db-88d7-eddd253172ba-profile_image-300x300.png",
    "user_offline_image_url": "https://static-cdn.jtvnw.net/jtv_user_pictures/2569a806-e6a8-4bb3-bd66-18f92b7a660a-channel_offline_image-1920x1080.png",
    "stream_id": 40187134443,
    "stream_game_id": "509658",
    "stream_game_name": "Just Chatting",
    "stream_title": "💖LA Angel💖",
    "stream_viewer_count": 1007,
    "stream_thumbnail_url": "https://static-cdn.jtvnw.net/previews-ttv/live_user_seoahtv-{width}x{height}.jpg"
  },
  {
    "user_id": 445080375,
    "user_login": "carabeanz",
    "user_display_name": "carabeanz",
    "user_broadcaster_type": "partner",
    "user_profile_image_url": "https://static-cdn.jtvnw.net/jtv_user_pictures/b5321f28-1733-4a17-8a0f-11c63ef68676-profile_image-300x300.png",
    "user_offline_image_url": "https://static-cdn.jtvnw.net/jtv_user_pictures/145b8180-c41e-42a0-bcc0-50f5cff69ba2-channel_offline_image-1920x1080.jpeg",
    "stream_id": 43731244652,
    "stream_game_id": "509658",
    "stream_game_name": "Just Chatting",
    "stream_title": "SUB SATURDAY CALLING ALL SUBS TO PLAY WITH ME 💕 !ig !sub !web ",
    "stream_viewer_count": 526,
    "stream_thumbnail_url": "https://static-cdn.jtvnw.net/previews-ttv/live_user_carabeanz-{width}x{height}.jpg"
  },
  {
    "user_id": 253366772,
    "user_login": "xianleeasmr",
    "user_display_name": "xianleeasmr",
    "user_broadcaster_type": "affiliate",
    "user_profile_image_url": "https://static-cdn.jtvnw.net/jtv_user_pictures/1e3c5431-cba2-4b15-8b0a-22479c8b2e91-profile_image-300x300.png",
    "user_offline_image_url": "",
    "stream_id": 43728536348,
    "stream_game_id": "509659",
    "stream_game_name": "ASMR",
    "stream_title": "💦ASMR 🍑Relaxing Ear Cleaning💦",
    "stream_viewer_count": 393,
    "stream_thumbnail_url": "https://static-cdn.jtvnw.net/previews-ttv/live_user_xianleeasmr-{width}x{height}.jpg"
  },
  {
    "user_id": 430642455,
    "user_login": "kristinemaia",
    "user_display_name": "kristinemaia",
    "user_broadcaster_type": "partner",
    "user_profile_image_url": "https://static-cdn.jtvnw.net/jtv_user_pictures/5b0333f0-646c-40ec-9f09-6e5de549eebc-profile_image-300x300.png",
    "user_offline_image_url": "https://static-cdn.jtvnw.net/jtv_user_pictures/e70cc6fb-7562-4412-a2c3-056561ecba1a-channel_offline_image-1920x1080.png",
    "stream_id": 44336098461,
    "stream_game_id": "509658",
    "stream_game_name": "Just Chatting",
    "stream_title": "FUN TIME WITH MY SISTER 💗☺️🌊 !socials !patreon ",
    "stream_viewer_count": 248,
    "stream_thumbnail_url": "https://static-cdn.jtvnw.net/previews-ttv/live_user_kristinemaia-{width}x{height}.jpg"
  },
  {
    "user_id": 193275014,
    "user_login": "starfmodel",
    "user_display_name": "Starfmodel",
    "user_broadcaster_type": "affiliate",
    "user_profile_image_url": "https://static-cdn.jtvnw.net/jtv_user_pictures/f614a01e-9589-4e55-9d6d-153571316d73-profile_image-300x300.png",
    "user_offline_image_url": "",
    "stream_id": 44337415309,
    "stream_game_id": "509658",
    "stream_game_name": "Just Chatting",
    "stream_title": "Nerf THIS! Hello cuties♡ !socials !discord ",
    "stream_viewer_count": 219,
    "stream_thumbnail_url": "https://static-cdn.jtvnw.net/previews-ttv/live_user_starfmodel-{width}x{height}.jpg"
  },
  {
    "user_id": 10180554,
    "user_login": "victorias",
    "user_display_name": "Victorias",
    "user_broadcaster_type": "partner",
    "user_profile_image_url": "https://static-cdn.jtvnw.net/jtv_user_pictures/d7abf2d7-b1dd-4b2d-be7f-2a6a253b5a3b-profile_image-300x300.png",
    "user_offline_image_url": "https://static-cdn.jtvnw.net/jtv_user_pictures/b3148712-8f0d-4d28-a7a8-fa189e727da2-channel_offline_image-1920x1080.png",
    "stream_id": 44335935901,
    "stream_game_id": "509658",
    "stream_game_name": "Just Chatting",
    "stream_title": "SUBATHON | TYPE --> !socials",
    "stream_viewer_count": 150,
    "stream_thumbnail_url": "https://static-cdn.jtvnw.net/previews-ttv/live_user_victorias-{width}x{height}.jpg"
  },
  {
    "user_id": 407496462,
    "user_login": "elfherself",
    "user_display_name": "ElfHerSelf",
    "user_broadcaster_type": "partner",
    "user_profile_image_url": "https://static-cdn.jtvnw.net/jtv_user_pictures/0c52f150-ff1e-4258-a5df-973499fa955d-profile_image-300x300.png",
    "user_offline_image_url": "https://static-cdn.jtvnw.net/jtv_user_pictures/f97ebbfc-d40f-4da6-b2f2-797e941d6d44-channel_offline_image-1920x1080.jpeg",
    "stream_id": 43729477036,
    "stream_game_id": "509658",
    "stream_game_name": "Just Chatting",
    "stream_title": "Jobs|!socials",
    "stream_viewer_count": 130,
    "stream_thumbnail_url": "https://static-cdn.jtvnw.net/previews-ttv/live_user_elfherself-{width}x{height}.jpg"
  },
  {
    "user_id": 103397701,
    "user_login": "varvaria",
    "user_display_name": "Varvaria",
    "user_broadcaster_type": "partner",
    "user_profile_image_url": "https://static-cdn.jtvnw.net/jtv_user_pictures/1cbb0127-8384-46ed-8973-d84ba3d1f777-profile_image-300x300.jpeg",
    "user_offline_image_url": "https://static-cdn.jtvnw.net/jtv_user_pictures/a4d10d91-4629-498c-aa39-9f8c524d20e6-channel_offline_image-1920x1080.jpeg",
    "stream_id": 43729839500,
    "stream_game_id": "509658",
    "stream_game_name": "Just Chatting",
    "stream_title": " Scary Alerts )) Let's have fun)",
    "stream_viewer_count": 104,
    "stream_thumbnail_url": "https://static-cdn.jtvnw.net/previews-ttv/live_user_varvaria-{width}x{height}.jpg"
  },
  {
    "user_id": 472921491,
    "user_login": "chanice_bonner",
    "user_display_name": "chanice_bonner",
    "user_broadcaster_type": "affiliate",
    "user_profile_image_url": "https://static-cdn.jtvnw.net/jtv_user_pictures/9710fa61-b240-401c-9de0-b70b56219e3b-profile_image-300x300.png",
    "user_offline_image_url": "",
    "stream_id": 44333385501,
    "stream_game_id": "32982",
    "stream_game_name": "Grand Theft Auto V",
    "stream_title": "IF YOU ARE IN HOUSTON COME BOOK A SECTION WITH ME AT MY CLUB DM ME FOR DETAILS 🔥 JOIN JAMROCK RP DISCORD COMING SOON❤JAMAICA'S FINEST❤",
    "stream_viewer_count": 84,
    "stream_thumbnail_url": "https://static-cdn.jtvnw.net/previews-ttv/live_user_chanice_bonner-{width}x{height}.jpg"
  },
  {
    "user_id": 488422566,
    "user_login": "twictoriches",
    "user_display_name": "twictoriches",
    "user_broadcaster_type": "affiliate",
    "user_profile_image_url": "https://static-cdn.jtvnw.net/jtv_user_pictures/d18703b9-2251-4e64-8fa3-3df12d2f47d9-profile_image-300x300.png",
    "user_offline_image_url": "https://static-cdn.jtvnw.net/jtv_user_pictures/575bfbfd-65e2-4aaf-8d81-612133c39e03-channel_offline_image-1920x1080.png",
    "stream_id": 44336013469,
    "stream_game_id": "509658",
    "stream_game_name": "Just Chatting",
    "stream_title": "Обзор: Обливион (начало в 20:20) !socials ",
    "stream_viewer_count": 58,
    "stream_thumbnail_url": "https://static-cdn.jtvnw.net/previews-ttv/live_user_twictoriches-{width}x{height}.jpg"
  },
  {
    "user_id": 609563512,
    "user_login": "leealiciaplays",
    "user_display_name": "Leealiciaplays",
    "user_broadcaster_type": "affiliate",
    "user_profile_image_url": "https://static-cdn.jtvnw.net/jtv_user_pictures/4ab9b904-4e95-4c62-88b0-6545c1170c16-profile_image-300x300.png",
    "user_offline_image_url": "https://static-cdn.jtvnw.net/jtv_user_pictures/a49b14d2-93ea-4ce1-9ed1-59caa6c74bb4-channel_offline_image-1920x1080.jpeg",
    "stream_id": 44335459085,
    "stream_game_id": "509658",
    "stream_game_name": "Just Chatting",
    "stream_title": "Hey you missed u! Any digital marketing experts here? ! Tier 2/3 get snapchat! socials",
    "stream_viewer_count": 56,
    "stream_thumbnail_url": "https://static-cdn.jtvnw.net/previews-ttv/live_user_leealiciaplays-{width}x{height}.jpg"
  },
  {
    "user_id": 530821239,
    "user_login": "simmykenz",
    "user_display_name": "SimmyKenz",
    "user_broadcaster_type": "partner",
    "user_profile_image_url": "https://static-cdn.jtvnw.net/jtv_user_pictures/deee3df8-3909-481c-92db-238175fd1e7e-profile_image-300x300.png",
    "user_offline_image_url": "",
    "stream_id": 43732157580,
    "stream_game_id": "518011",
    "stream_game_name": "HITMAN 3",
    "stream_title": "femme fatale plays hitman (backseating encouraged:)",
    "stream_viewer_count": 36,
    "stream_thumbnail_url": "https://static-cdn.jtvnw.net/previews-ttv/live_user_simmykenz-{width}x{height}.jpg"
  },
  {
    "user_id": 734268491,
    "user_login": "olgasparkz",
    "user_display_name": "olgasparkz",
    "user_broadcaster_type": "affiliate",
    "user_profile_image_url": "https://static-cdn.jtvnw.net/jtv_user_pictures/f1677785-8f2c-4af9-8d0d-eec2c1e73646-profile_image-300x300.png",
    "user_offline_image_url": "",
    "stream_id": 43732438860,
    "stream_game_id": "116747788",
    "stream_game_name": "Pools, Hot Tubs, and Beaches",
    "stream_title": "PINK FLAMINGO AFTERPARTY !ig ",
    "stream_viewer_count": 17,
    "stream_thumbnail_url": "https://static-cdn.jtvnw.net/previews-ttv/live_user_olgasparkz-{width}x{height}.jpg"
  }
]
