[
  {
    "user_id": 125387632,
    "user_login": "amouranth",
    "user_display_name": "Amouranth",
    "user_broadcaster_type": "partner",
    "user_profile_image_url": "https://static-cdn.jtvnw.net/jtv_user_pictures/8aa0b7dc-e4b0-4666-a99f-5d62d9bf168a-profile_image-300x300.png",
    "user_offline_image_url": "https://static-cdn.jtvnw.net/jtv_user_pictures/2509e087-402b-4d18-a813-d9bd478b92c1-channel_offline_image-1920x1080.png",
    "stream_id": 44640164477,
    "stream_game_id": "413353439",
    "stream_game_name": "Just Dance 2022",
    "stream_title": "ðŸŽˆBIRTHDAY TONIGHTðŸ’¦!s-->social media linksðŸ’¦NEW MERCH --> !waifuðŸ’¦ !pobox !wishlist",
    "stream_viewer_count": 8342,
    "stream_thumbnail_url": "https://static-cdn.jtvnw.net/previews-ttv/live_user_amouranth-{width}x{height}.jpg"
  },
  {
    "user_id": 457124238,
    "user_login": "adrianachechik_",
    "user_display_name": "AdrianaChechik_",
    "user_broadcaster_type": "partner",
    "user_profile_image_url": "https://static-cdn.jtvnw.net/jtv_user_pictures/cecd28e9-df32-441a-9a1f-54e2ff7722ab-profile_image-300x300.png",
    "user_offline_image_url": "https://static-cdn.jtvnw.net/jtv_user_pictures/da3337d3-5d28-4e7e-9d24-5ee9a4cbb222-channel_offline_image-1920x1080.png",
    "stream_id": 44642464381,
    "stream_game_id": "509658",
    "stream_game_name": "Just Chatting",
    "stream_title": "Decorating the tree!!",
    "stream_viewer_count": 1464,
    "stream_thumbnail_url": "https://static-cdn.jtvnw.net/previews-ttv/live_user_adrianachechik_-{width}x{height}.jpg"
  },
  {
    "user_id": 715774157,
    "user_login": "mstriggahappy_",
    "user_display_name": "MsTriggaHappy_",
    "user_broadcaster_type": "",
    "user_profile_image_url": "https://static-cdn.jtvnw.net/jtv_user_pictures/54ce3310-fe77-43bd-b5ec-b33a01462de8-profile_image-300x300.png",
    "user_offline_image_url": "",
    "stream_id": 44641071757,
    "stream_game_id": "116747788",
    "stream_game_name": "Pools, Hot Tubs, and Beaches",
    "stream_title": "Southern Belle !tiktok",
    "stream_viewer_count": 629,
    "stream_thumbnail_url": "https://static-cdn.jtvnw.net/previews-ttv/live_user_mstriggahappy_-{width}x{height}.jpg"
  },
  {
    "user_id": 160882737,
    "user_login": "tamiresbarbosa",
    "user_display_name": "Tamiresbarbosa",
    "user_broadcaster_type": "affiliate",
    "user_profile_image_url": "https://static-cdn.jtvnw.net/jtv_user_pictures/fee3a4e6-7c4a-46f1-86c8-1441c172a121-profile_image-300x300.png",
    "user_offline_image_url": "https://static-cdn.jtvnw.net/jtv_user_pictures/e6888fe3-cbe9-41b5-830a-0c8d36a09f26-channel_offline_image-1920x1080.jpeg",
    "stream_id": 44641307709,
    "stream_game_id": "509658",
    "stream_game_name": "Just Chatting",
    "stream_title": "+18  !BTIS !WHATSAPP !DANÃ‡A",
    "stream_viewer_count": 508,
    "stream_thumbnail_url": "https://static-cdn.jtvnw.net/previews-ttv/live_user_tamiresbarbosa-{width}x{height}.jpg"
  },
  {
    "user_id": 486289378,
    "user_login": "peachling",
    "user_display_name": "Peachling",
    "user_broadcaster_type": "partner",
    "user_profile_image_url": "https://static-cdn.jtvnw.net/jtv_user_pictures/080cd356-1589-4b2a-b731-25666b86de0a-profile_image-300x300.png",
    "user_offline_image_url": "https://static-cdn.jtvnw.net/jtv_user_pictures/24060a30-6ada-4bed-a06b-398820fd7555-channel_offline_image-1920x1080.png",
    "stream_id": 44641597933,
    "stream_game_id": "509659",
    "stream_game_name": "ASMR",
    "stream_title": "ðŸ‘ S TIER EAR LICKS ðŸ‘ !s !insta",
    "stream_viewer_count": 284,
    "stream_thumbnail_url": "https://static-cdn.jtvnw.net/previews-ttv/live_user_peachling-{width}x{height}.jpg"
  },
  {
    "user_id": 237238176,
    "user_login": "seolyihyeon",
    "user_display_name": "ì„¤ì´í˜„",
    "user_broadcaster_type": "partner",
    "user_profile_image_url": "https://static-cdn.jtvnw.net/jtv_user_pictures/c5500685-1002-487c-a6c2-5d54668d7063-profile_image-300x300.png",
    "user_offline_image_url": "https://static-cdn.jtvnw.net/jtv_user_pictures/edbd2b5a-de9d-4429-bb1b-a478a7af66fb-channel_offline_image-1920x1080.png",
    "stream_id": 44642273821,
    "stream_game_id": "509658",
    "stream_game_name": "Just Chatting",
    "stream_title": "12/2â™¡âƒ°  ìš°ë¦¬ íŠ¸ìˆ˜ ë–¡ë³¶ì´ ì¢‹ì•„í•´? ë–¡ë³¶ì´ ë¨¹ê³ ê°ˆëž˜?",
    "stream_viewer_count": 232,
    "stream_thumbnail_url": "https://static-cdn.jtvnw.net/previews-ttv/live_user_seolyihyeon-{width}x{height}.jpg"
  },
  {
    "user_id": 148114007,
    "user_login": "rayrachel",
    "user_display_name": "RayRachel",
    "user_broadcaster_type": "partner",
    "user_profile_image_url": "https://static-cdn.jtvnw.net/jtv_user_pictures/ae41397a-b2fe-4223-a188-3d3b3b4dbdbe-profile_image-300x300.png",
    "user_offline_image_url": "https://static-cdn.jtvnw.net/jtv_user_pictures/a942ea9f-f524-4904-80f5-0dee5e339446-channel_offline_image-1920x1080.jpeg",
    "stream_id": 44641194109,
    "stream_game_id": "509658",
    "stream_game_name": "Just Chatting",
    "stream_title": "Just Chatting",
    "stream_viewer_count": 230,
    "stream_thumbnail_url": "https://static-cdn.jtvnw.net/previews-ttv/live_user_rayrachel-{width}x{height}.jpg"
  },
  {
    "user_id": 420015559,
    "user_login": "basicbimboo",
    "user_display_name": "BasicBimboo",
    "user_broadcaster_type": "partner",
    "user_profile_image_url": "https://static-cdn.jtvnw.net/jtv_user_pictures/5acbae9d-2a67-41e0-9142-025e3f98999a-profile_image-300x300.png",
    "user_offline_image_url": "",
    "stream_id": 43957789020,
    "stream_game_id": "509658",
    "stream_game_name": "Just Chatting",
    "stream_title": "AVERAGE LOOKING BLONDE LADY WITH VERY LONG ROOTS PUTS TOGETHER A TREE. HOW LONG DO YOU THINK IT WILL TAKE? IDK MAN COME SEE WOWZERS| !donate",
    "stream_viewer_count": 192,
    "stream_thumbnail_url": "https://static-cdn.jtvnw.net/previews-ttv/live_user_basicbimboo-{width}x{height}.jpg"
  },
  {
    "user_id": 10180554,
    "user_login": "victorias",
    "user_display_name": "Victorias",
    "user_broadcaster_type": "partner",
    "user_profile_image_url": "https://static-cdn.jtvnw.net/jtv_user_pictures/d7abf2d7-b1dd-4b2d-be7f-2a6a253b5a3b-profile_image-300x300.png",
    "user_offline_image_url": "https://static-cdn.jtvnw.net/jtv_user_pictures/b3148712-8f0d-4d28-a7a8-fa189e727da2-channel_offline_image-1920x1080.png",
    "stream_id": 44640957181,
    "stream_game_id": "509658",
    "stream_game_name": "Just Chatting",
    "stream_title": "SAN DIEGO IRL  | TYPE --> !socials",
    "stream_viewer_count": 131,
    "stream_thumbnail_url": "https://static-cdn.jtvnw.net/previews-ttv/live_user_victorias-{width}x{height}.jpg"
  },
  {
    "user_id": 475171674,
    "user_login": "befitpilatesgal",
    "user_display_name": "BeFitPilatesGal",
    "user_broadcaster_type": "partner",
    "user_profile_image_url": "https://static-cdn.jtvnw.net/jtv_user_pictures/3b061b62-5f64-48d6-803a-ce4f39870f6e-profile_image-300x300.png",
    "user_offline_image_url": "https://static-cdn.jtvnw.net/jtv_user_pictures/fde08b9c-b2c6-46e8-89ca-21634619ad4a-channel_offline_image-1920x1080.jpeg",
    "stream_id": 44639455085,
    "stream_game_id": "509658",
    "stream_game_name": "Just Chatting",
    "stream_title": "ðŸ”¥1YR PARTNER POLE PARTY ANNIVERSARY 18+ðŸ”¥",
    "stream_viewer_count": 93,
    "stream_thumbnail_url": "https://static-cdn.jtvnw.net/previews-ttv/live_user_befitpilatesgal-{width}x{height}.jpg"
  },
  {
    "user_id": 530821239,
    "user_login": "simmykenz",
    "user_display_name": "SimmyKenz",
    "user_broadcaster_type": "partner",
    "user_profile_image_url": "https://static-cdn.jtvnw.net/jtv_user_pictures/deee3df8-3909-481c-92db-238175fd1e7e-profile_image-300x300.png",
    "user_offline_image_url": "",
    "stream_id": 43959199980,
    "stream_game_id": "509658",
    "stream_game_name": "Just Chatting",
    "stream_title": "Who's the secret vegan?",
    "stream_viewer_count": 70,
    "stream_thumbnail_url": "https://static-cdn.jtvnw.net/previews-ttv/live_user_simmykenz-{width}x{height}.jpg"
  },
  {
    "user_id": 280116605,
    "user_login": "kayleerosevera",
    "user_display_name": "KayleeRoseVera",
    "user_broadcaster_type": "affiliate",
    "user_profile_image_url": "https://static-cdn.jtvnw.net/jtv_user_pictures/1edbcaa9-1fe9-471a-baef-afb457826899-profile_image-300x300.png",
    "user_offline_image_url": "https://static-cdn.jtvnw.net/jtv_user_pictures/6137a344-e8dc-430e-898d-ea37f0679a6f-channel_offline_image-1920x1080.jpeg",
    "stream_id": 40281194155,
    "stream_game_id": "509658",
    "stream_game_name": "Just Chatting",
    "stream_title": "L-O-V-E PLEASE COME TO ME ðŸ’– !socials !snap !donate",
    "stream_viewer_count": 42,
    "stream_thumbnail_url": "https://static-cdn.jtvnw.net/previews-ttv/live_user_kayleerosevera-{width}x{height}.jpg"
  },
  {
    "user_id": 89791124,
    "user_login": "leah_ayame",
    "user_display_name": "Leah_Ayame",
    "user_broadcaster_type": "affiliate",
    "user_profile_image_url": "https://static-cdn.jtvnw.net/jtv_user_pictures/69124f0e-d087-49cd-af3d-a07a36abe3e7-profile_image-300x300.png",
    "user_offline_image_url": "",
    "stream_id": 43959875148,
    "stream_game_id": "116747788",
    "stream_game_name": "Pools, Hot Tubs, and Beaches",
    "stream_title": "New bikinis!! Come judge them ",
    "stream_viewer_count": 38,
    "stream_thumbnail_url": "https://static-cdn.jtvnw.net/previews-ttv/live_user_leah_ayame-{width}x{height}.jpg"
  },
  {
    "user_id": 711208908,
    "user_login": "yntmoe",
    "user_display_name": "Yntmoe",
    "user_broadcaster_type": "affiliate",
    "user_profile_image_url": "https://static-cdn.jtvnw.net/jtv_user_pictures/1ecfccaa-dc8f-432c-a0fd-ae8c92904e56-profile_image-300x300.png",
    "user_offline_image_url": "",
    "stream_id": 43955817516,
    "stream_game_id": "116747788",
    "stream_game_name": "Pools, Hot Tubs, and Beaches",
    "stream_title": "Bikini Contest",
    "stream_viewer_count": 23,
    "stream_thumbnail_url": "https://static-cdn.jtvnw.net/previews-ttv/live_user_yntmoe-{width}x{height}.jpg"
  },
  {
    "user_id": 518269329,
    "user_login": "sheblackout",
    "user_display_name": "sheblackout",
    "user_broadcaster_type": "affiliate",
    "user_profile_image_url": "https://static-cdn.jtvnw.net/jtv_user_pictures/083576f1-f763-47b0-a9b8-c9f1f5a1e0f3-profile_image-300x300.png",
    "user_offline_image_url": "https://static-cdn.jtvnw.net/jtv_user_pictures/5a556bee-03c2-4b5d-ab84-8e8d9bd0db00-channel_offline_image-1920x1080.png",
    "stream_id": 43959891516,
    "stream_game_id": "509658",
    "stream_game_name": "Just Chatting",
    "stream_title": "|FR\\EN| |quebec| my life is a mess, but can I be your friend ????  !socials ",
    "stream_viewer_count": 4,
    "stream_thumbnail_url": "https://static-cdn.jtvnw.net/previews-ttv/live_user_sheblackout-{width}x{height}.jpg"
  }
]
