[
  {
    "user_id": 125387632,
    "user_login": "amouranth",
    "user_display_name": "Amouranth",
    "user_broadcaster_type": "partner",
    "user_profile_image_url": "https://static-cdn.jtvnw.net/jtv_user_pictures/8aa0b7dc-e4b0-4666-a99f-5d62d9bf168a-profile_image-300x300.png",
    "user_offline_image_url": "https://static-cdn.jtvnw.net/jtv_user_pictures/2509e087-402b-4d18-a813-d9bd478b92c1-channel_offline_image-1920x1080.png",
    "stream_id": 44671756957,
    "stream_game_id": "413353439",
    "stream_game_name": "Just Dance 2022",
    "stream_title": "DANCING🎈BIRTHDAY WEEKEND💦!s-->social media links💦",
    "stream_viewer_count": 9797,
    "stream_thumbnail_url": "https://static-cdn.jtvnw.net/previews-ttv/live_user_amouranth-{width}x{height}.jpg"
  },
  {
    "user_id": 61974931,
    "user_login": "leynainu",
    "user_display_name": "Leynainu",
    "user_broadcaster_type": "partner",
    "user_profile_image_url": "https://static-cdn.jtvnw.net/jtv_user_pictures/0971fcf6-c381-456a-848a-09889c20428a-profile_image-300x300.png",
    "user_offline_image_url": "https://static-cdn.jtvnw.net/jtv_user_pictures/c09dc972-31af-4b4b-8c94-15f4262343f1-channel_offline_image-1920x1080.jpeg",
    "stream_id": 44671700909,
    "stream_game_id": "509659",
    "stream_game_name": "ASMR",
    "stream_title": "💋Double D'io💋/!YT > NEW VIDEO /  !social = all my Social Media",
    "stream_viewer_count": 4456,
    "stream_thumbnail_url": "https://static-cdn.jtvnw.net/previews-ttv/live_user_leynainu-{width}x{height}.jpg"
  },
  {
    "user_id": 409624608,
    "user_login": "melina",
    "user_display_name": "melina",
    "user_broadcaster_type": "partner",
    "user_profile_image_url": "https://static-cdn.jtvnw.net/jtv_user_pictures/03ed0dc1-683a-4db0-ac12-16f0573b6be2-profile_image-300x300.png",
    "user_offline_image_url": "",
    "stream_id": 44674886493,
    "stream_game_id": "509658",
    "stream_game_name": "Just Chatting",
    "stream_title": "COMIC CON! LA  will we find Jinnytty and Kyootbot? | insta: melina.goransson",
    "stream_viewer_count": 2306,
    "stream_thumbnail_url": "https://static-cdn.jtvnw.net/previews-ttv/live_user_melina-{width}x{height}.jpg"
  },
  {
    "user_id": 544502795,
    "user_login": "ibabyrainbow",
    "user_display_name": "ibabyrainbow",
    "user_broadcaster_type": "partner",
    "user_profile_image_url": "https://static-cdn.jtvnw.net/jtv_user_pictures/71204832-58f1-47e1-af54-affd7d27def2-profile_image-300x300.png",
    "user_offline_image_url": "https://static-cdn.jtvnw.net/jtv_user_pictures/0ad58853-b5d9-4b39-a018-e84fc36eb2fa-channel_offline_image-1920x1080.jpeg",
    "stream_id": 44671691853,
    "stream_game_id": "509658",
    "stream_game_name": "Just Chatting",
    "stream_title": "baking & xmas parade later",
    "stream_viewer_count": 1361,
    "stream_thumbnail_url": "https://static-cdn.jtvnw.net/previews-ttv/live_user_ibabyrainbow-{width}x{height}.jpg"
  },
  {
    "user_id": 98578318,
    "user_login": "ivysky",
    "user_display_name": "IvySky",
    "user_broadcaster_type": "partner",
    "user_profile_image_url": "https://static-cdn.jtvnw.net/jtv_user_pictures/e0201698-b61c-409e-9d50-d9906352cd6f-profile_image-300x300.png",
    "user_offline_image_url": "",
    "stream_id": 40295882427,
    "stream_game_id": "509658",
    "stream_game_name": "Just Chatting",
    "stream_title": "!RULES1 Fashion Nova Try On Haul & Drinks <(♡_♡<) Day 46/100",
    "stream_viewer_count": 893,
    "stream_thumbnail_url": "https://static-cdn.jtvnw.net/previews-ttv/live_user_ivysky-{width}x{height}.jpg"
  },
  {
    "user_id": 252393390,
    "user_login": "imviolet_",
    "user_display_name": "imviolet_",
    "user_broadcaster_type": "partner",
    "user_profile_image_url": "https://static-cdn.jtvnw.net/jtv_user_pictures/1332bdaf-b3da-4a22-bcba-72aa139317f5-profile_image-300x300.png",
    "user_offline_image_url": "https://static-cdn.jtvnw.net/jtv_user_pictures/20afe8a1-3536-49cc-99b2-8bbc3c4b417e-channel_offline_image-1920x1080.png",
    "stream_id": 43979848220,
    "stream_game_id": "509658",
    "stream_game_name": "Just Chatting",
    "stream_title": "SPOILER NEXT COSPLAY 🍋 !shorts !mondiali 💦",
    "stream_viewer_count": 839,
    "stream_thumbnail_url": "https://static-cdn.jtvnw.net/previews-ttv/live_user_imviolet_-{width}x{height}.jpg"
  },
  {
    "user_id": 451578537,
    "user_login": "krypto_nat",
    "user_display_name": "krypto_nat",
    "user_broadcaster_type": "partner",
    "user_profile_image_url": "https://static-cdn.jtvnw.net/jtv_user_pictures/d68e91c1-478d-48c1-a6fc-8afb256e84aa-profile_image-300x300.png",
    "user_offline_image_url": "https://static-cdn.jtvnw.net/jtv_user_pictures/c31d2b17-1784-411a-8e2c-ef4a9e009d98-channel_offline_image-1920x1080.jpeg",
    "stream_id": 40296296955,
    "stream_game_id": "509658",
    "stream_game_name": "Just Chatting",
    "stream_title": "wrong stream !social +18.5",
    "stream_viewer_count": 655,
    "stream_thumbnail_url": "https://static-cdn.jtvnw.net/previews-ttv/live_user_krypto_nat-{width}x{height}.jpg"
  },
  {
    "user_id": 629538285,
    "user_login": "nickykittyxx",
    "user_display_name": "nickykittyxx",
    "user_broadcaster_type": "affiliate",
    "user_profile_image_url": "https://static-cdn.jtvnw.net/jtv_user_pictures/dc80c7d2-7d51-4db4-b340-9de901f0f95d-profile_image-300x300.png",
    "user_offline_image_url": "",
    "stream_id": 44674682669,
    "stream_game_id": "509658",
    "stream_game_name": "Just Chatting",
    "stream_title": "La comic con ✨",
    "stream_viewer_count": 654,
    "stream_thumbnail_url": "https://static-cdn.jtvnw.net/previews-ttv/live_user_nickykittyxx-{width}x{height}.jpg"
  },
  {
    "user_id": 505105909,
    "user_login": "lina_asmr",
    "user_display_name": "lina_asmr",
    "user_broadcaster_type": "partner",
    "user_profile_image_url": "https://static-cdn.jtvnw.net/jtv_user_pictures/0b7756a1-dad0-47f6-b51f-ee22fedb8347-profile_image-300x300.png",
    "user_offline_image_url": "https://static-cdn.jtvnw.net/jtv_user_pictures/f7ea614a-c986-44b9-a0d5-5ae53a556d4d-channel_offline_image-1920x1080.jpeg",
    "stream_id": 40293838891,
    "stream_game_id": "116747788",
    "stream_game_name": "Pools, Hot Tubs, and Beaches",
    "stream_title": "Super pool and beach !yt [rerun][ENG only]",
    "stream_viewer_count": 488,
    "stream_thumbnail_url": "https://static-cdn.jtvnw.net/previews-ttv/live_user_lina_asmr-{width}x{height}.jpg"
  },
  {
    "user_id": 124069501,
    "user_login": "emmalayne",
    "user_display_name": "EmmaLayne",
    "user_broadcaster_type": "affiliate",
    "user_profile_image_url": "https://static-cdn.jtvnw.net/jtv_user_pictures/emmalayne-profile_image-8dcc8c3b14ea11c9-300x300.png",
    "user_offline_image_url": "https://static-cdn.jtvnw.net/jtv_user_pictures/421d5632-0955-4937-adc1-8cac52a1a070-channel_offline_image-1920x1080.jpeg",
    "stream_id": 44672453341,
    "stream_game_id": "116747788",
    "stream_game_name": "Pools, Hot Tubs, and Beaches",
    "stream_title": "Hot tub 💦  !socials",
    "stream_viewer_count": 461,
    "stream_thumbnail_url": "https://static-cdn.jtvnw.net/previews-ttv/live_user_emmalayne-{width}x{height}.jpg"
  },
  {
    "user_id": 434734417,
    "user_login": "allecakes",
    "user_display_name": "allecakes",
    "user_broadcaster_type": "partner",
    "user_profile_image_url": "https://static-cdn.jtvnw.net/jtv_user_pictures/3280ac85-6f7a-427f-9ed7-2f9bc82541f7-profile_image-300x300.png",
    "user_offline_image_url": "https://static-cdn.jtvnw.net/jtv_user_pictures/095ae1c9-a571-489d-b347-4f524f54d99c-channel_offline_image-1920x1080.jpeg",
    "stream_id": 43981814668,
    "stream_game_id": "509658",
    "stream_game_name": "Just Chatting",
    "stream_title": "Exploring with @meowycake @cliffdotsun @mistymaps💗 !mary !socials ",
    "stream_viewer_count": 263,
    "stream_thumbnail_url": "https://static-cdn.jtvnw.net/previews-ttv/live_user_allecakes-{width}x{height}.jpg"
  },
  {
    "user_id": 445080375,
    "user_login": "carabeanz",
    "user_display_name": "carabeanz",
    "user_broadcaster_type": "partner",
    "user_profile_image_url": "https://static-cdn.jtvnw.net/jtv_user_pictures/b5321f28-1733-4a17-8a0f-11c63ef68676-profile_image-300x300.png",
    "user_offline_image_url": "https://static-cdn.jtvnw.net/jtv_user_pictures/145b8180-c41e-42a0-bcc0-50f5cff69ba2-channel_offline_image-1920x1080.jpeg",
    "stream_id": 43982711916,
    "stream_game_id": "509658",
    "stream_game_name": "Just Chatting",
    "stream_title": "TITLES ARE SO HARD✨ !social !web !sub",
    "stream_viewer_count": 258,
    "stream_thumbnail_url": "https://static-cdn.jtvnw.net/previews-ttv/live_user_carabeanz-{width}x{height}.jpg"
  },
  {
    "user_id": 499133068,
    "user_login": "shulyyyyyy",
    "user_display_name": "shulyyyyyy",
    "user_broadcaster_type": "partner",
    "user_profile_image_url": "https://static-cdn.jtvnw.net/jtv_user_pictures/14011d14-6f36-4975-a191-5fee17f0728c-profile_image-300x300.png",
    "user_offline_image_url": "",
    "stream_id": 40294938731,
    "stream_game_id": "509658",
    "stream_game_name": "Just Chatting",
    "stream_title": "Hi!  COSPLAY🤤😈   !inks !inst  !tg ",
    "stream_viewer_count": 240,
    "stream_thumbnail_url": "https://static-cdn.jtvnw.net/previews-ttv/live_user_shulyyyyyy-{width}x{height}.jpg"
  },
  {
    "user_id": 568694723,
    "user_login": "candycatcris",
    "user_display_name": "candycatcris",
    "user_broadcaster_type": "affiliate",
    "user_profile_image_url": "https://static-cdn.jtvnw.net/jtv_user_pictures/64994cb9-cbdd-423f-8294-ed48681042aa-profile_image-300x300.png",
    "user_offline_image_url": "https://static-cdn.jtvnw.net/jtv_user_pictures/3e0f0888-2672-437c-83b1-98edc72e550e-channel_offline_image-1920x1080.jpeg",
    "stream_id": 43980755948,
    "stream_game_id": "509658",
    "stream_game_name": "Just Chatting",
    "stream_title": "imagine touching butts 🍑 !pop !s !fit",
    "stream_viewer_count": 225,
    "stream_thumbnail_url": "https://static-cdn.jtvnw.net/previews-ttv/live_user_candycatcris-{width}x{height}.jpg"
  },
  {
    "user_id": 420015559,
    "user_login": "basicbimboo",
    "user_display_name": "BasicBimboo",
    "user_broadcaster_type": "partner",
    "user_profile_image_url": "https://static-cdn.jtvnw.net/jtv_user_pictures/5acbae9d-2a67-41e0-9142-025e3f98999a-profile_image-300x300.png",
    "user_offline_image_url": "",
    "stream_id": 43981635452,
    "stream_game_id": "509658",
    "stream_game_name": "Just Chatting",
    "stream_title": "OMG AWKWARD DANCING MAID TRIES HER BEST TO BE AMOURANTH BUT IS NOT ABLE TO BE. PLZ VALIDATE ME THX  | !donate",
    "stream_viewer_count": 193,
    "stream_thumbnail_url": "https://static-cdn.jtvnw.net/previews-ttv/live_user_basicbimboo-{width}x{height}.jpg"
  },
  {
    "user_id": 635001460,
    "user_login": "littleaznchat",
    "user_display_name": "LittleAznChat",
    "user_broadcaster_type": "partner",
    "user_profile_image_url": "https://static-cdn.jtvnw.net/jtv_user_pictures/26220bea-ed00-44fb-ad46-5d6a1622a43f-profile_image-300x300.png",
    "user_offline_image_url": "",
    "stream_id": 40295195419,
    "stream_game_id": "509658",
    "stream_game_name": "Just Chatting",
    "stream_title": "DAY 6/7 days of CHAT:💜 TIS THE NEW SEASON OF FN!!!",
    "stream_viewer_count": 177,
    "stream_thumbnail_url": "https://static-cdn.jtvnw.net/previews-ttv/live_user_littleaznchat-{width}x{height}.jpg"
  },
  {
    "user_id": 628967771,
    "user_login": "chickenwingcandy",
    "user_display_name": "ChickenWingCandy",
    "user_broadcaster_type": "affiliate",
    "user_profile_image_url": "https://static-cdn.jtvnw.net/jtv_user_pictures/ce43a79d-5616-44ec-ad8c-0a410b45fced-profile_image-300x300.png",
    "user_offline_image_url": "https://static-cdn.jtvnw.net/jtv_user_pictures/d60703ed-71f9-425d-968b-231400c2bcb0-channel_offline_image-1920x1080.jpeg",
    "stream_id": 43981752812,
    "stream_game_id": "506416",
    "stream_game_name": "Halo Infinite",
    "stream_title": "Hello  :) !linktree !discord English only Please",
    "stream_viewer_count": 161,
    "stream_thumbnail_url": "https://static-cdn.jtvnw.net/previews-ttv/live_user_chickenwingcandy-{width}x{height}.jpg"
  },
  {
    "user_id": 49953078,
    "user_login": "tinycowgirl",
    "user_display_name": "tinycowgirl",
    "user_broadcaster_type": "partner",
    "user_profile_image_url": "https://static-cdn.jtvnw.net/jtv_user_pictures/0e43fe4e-212f-475f-a1c1-d472d8d9d92e-profile_image-300x300.png",
    "user_offline_image_url": "https://static-cdn.jtvnw.net/jtv_user_pictures/7aa9a8ee-3866-43e5-89c5-9f803a63c330-channel_offline_image-1920x1080.jpeg",
    "stream_id": 44674541213,
    "stream_game_id": "509658",
    "stream_game_name": "Just Chatting",
    "stream_title": "Should I clean out my closet? #sponsored Today's Stream is Sponsored by Clawee for Mobile !clawee !throne !fanhouse !amazon !nametag !s",
    "stream_viewer_count": 127,
    "stream_thumbnail_url": "https://static-cdn.jtvnw.net/previews-ttv/live_user_gillianaprils-{width}x{height}.jpg"
  },
  {
    "user_id": 539685432,
    "user_login": "winndago",
    "user_display_name": "winndago",
    "user_broadcaster_type": "affiliate",
    "user_profile_image_url": "https://static-cdn.jtvnw.net/jtv_user_pictures/a3a1b1c9-8495-41ba-b699-d71a56a747e4-profile_image-300x300.png",
    "user_offline_image_url": "",
    "stream_id": 43982638172,
    "stream_game_id": "413353439",
    "stream_game_name": "Just Dance 2022",
    "stream_title": "Tipsy dance stream✨!join !socials !wishlist 35% off spicy website💦",
    "stream_viewer_count": 125,
    "stream_thumbnail_url": "https://static-cdn.jtvnw.net/previews-ttv/live_user_winndago-{width}x{height}.jpg"
  },
  {
    "user_id": 104211056,
    "user_login": "calistamelissa",
    "user_display_name": "CalistaMelissa",
    "user_broadcaster_type": "affiliate",
    "user_profile_image_url": "https://static-cdn.jtvnw.net/jtv_user_pictures/440db7cf-7812-432e-becb-a3efc044e453-profile_image-300x300.png",
    "user_offline_image_url": "",
    "stream_id": 44674550253,
    "stream_game_id": "509658",
    "stream_game_name": "Just Chatting",
    "stream_title": "My ears fell off",
    "stream_viewer_count": 123,
    "stream_thumbnail_url": "https://static-cdn.jtvnw.net/previews-ttv/live_user_calistamelissa-{width}x{height}.jpg"
  },
  {
    "user_id": 10180554,
    "user_login": "victorias",
    "user_display_name": "Victorias",
    "user_broadcaster_type": "partner",
    "user_profile_image_url": "https://static-cdn.jtvnw.net/jtv_user_pictures/d7abf2d7-b1dd-4b2d-be7f-2a6a253b5a3b-profile_image-300x300.png",
    "user_offline_image_url": "https://static-cdn.jtvnw.net/jtv_user_pictures/b3148712-8f0d-4d28-a7a8-fa189e727da2-channel_offline_image-1920x1080.png",
    "stream_id": 44675214797,
    "stream_game_id": "509658",
    "stream_game_name": "Just Chatting",
    "stream_title": "SAN DIEGO HOLIDAY IRL | TYPE --> !socials",
    "stream_viewer_count": 82,
    "stream_thumbnail_url": "https://static-cdn.jtvnw.net/previews-ttv/live_user_victorias-{width}x{height}.jpg"
  },
  {
    "user_id": 475171674,
    "user_login": "befitpilatesgal",
    "user_display_name": "BeFitPilatesGal",
    "user_broadcaster_type": "partner",
    "user_profile_image_url": "https://static-cdn.jtvnw.net/jtv_user_pictures/3b061b62-5f64-48d6-803a-ce4f39870f6e-profile_image-300x300.png",
    "user_offline_image_url": "https://static-cdn.jtvnw.net/jtv_user_pictures/fde08b9c-b2c6-46e8-89ca-21634619ad4a-channel_offline_image-1920x1080.jpeg",
    "stream_id": 44674950029,
    "stream_game_id": "509658",
    "stream_game_name": "Just Chatting",
    "stream_title": "🔥HOLIDAY DANCE PARTY WERKOUT/STRETCH & COOK 18+ 🔥",
    "stream_viewer_count": 61,
    "stream_thumbnail_url": "https://static-cdn.jtvnw.net/previews-ttv/live_user_befitpilatesgal-{width}x{height}.jpg"
  },
  {
    "user_id": 700260006,
    "user_login": "vetatori",
    "user_display_name": "Vetatori",
    "user_broadcaster_type": "affiliate",
    "user_profile_image_url": "https://static-cdn.jtvnw.net/jtv_user_pictures/31be6d20-fd64-4cd4-9773-03a42abf735b-profile_image-300x300.png",
    "user_offline_image_url": "",
    "stream_id": 44671541069,
    "stream_game_id": "509658",
    "stream_game_name": "Just Chatting",
    "stream_title": "Draw Picture  !ig !sub",
    "stream_viewer_count": 59,
    "stream_thumbnail_url": "https://static-cdn.jtvnw.net/previews-ttv/live_user_vetatori-{width}x{height}.jpg"
  },
  {
    "user_id": 190140376,
    "user_login": "connie4u",
    "user_display_name": "connie4u",
    "user_broadcaster_type": "partner",
    "user_profile_image_url": "https://static-cdn.jtvnw.net/jtv_user_pictures/fb3d0528-effa-40c1-867c-eeba3c928c63-profile_image-300x300.png",
    "user_offline_image_url": "https://static-cdn.jtvnw.net/jtv_user_pictures/e972f8b4-5d6e-4d8f-81eb-eaec9ac0b639-channel_offline_image-1920x1080.png",
    "stream_id": 43979432844,
    "stream_game_id": "512710",
    "stream_game_name": "Call of Duty: Warzone",
    "stream_title": "GAMER GIRL GAINS REAL GAMER STREET CRED BY DOMINATING ANY GAMING TASK AND ENEMY IN HER WAY (VERY REAL) !insta !twitter",
    "stream_viewer_count": 52,
    "stream_thumbnail_url": "https://static-cdn.jtvnw.net/previews-ttv/live_user_connie4u-{width}x{height}.jpg"
  },
  {
    "user_id": 594619695,
    "user_login": "evathediiva",
    "user_display_name": "EvaTheDiiva",
    "user_broadcaster_type": "affiliate",
    "user_profile_image_url": "https://static-cdn.jtvnw.net/jtv_user_pictures/344d574a-2b13-44ae-8962-474731097afa-profile_image-300x300.png",
    "user_offline_image_url": "https://static-cdn.jtvnw.net/jtv_user_pictures/1cfa0e9e-ba2d-4aee-838d-60c9b5aa7760-channel_offline_image-1920x1080.png",
    "stream_id": 44670953981,
    "stream_game_id": "509658",
    "stream_game_name": "Just Chatting",
    "stream_title": "[EN/DE/RO] 1600 km roadtrip with Ella ! We go see our parents ! ❤❤❤",
    "stream_viewer_count": 49,
    "stream_thumbnail_url": "https://static-cdn.jtvnw.net/previews-ttv/live_user_evathediiva-{width}x{height}.jpg"
  },
  {
    "user_id": 711208908,
    "user_login": "yntmoe",
    "user_display_name": "Yntmoe",
    "user_broadcaster_type": "affiliate",
    "user_profile_image_url": "https://static-cdn.jtvnw.net/jtv_user_pictures/1ecfccaa-dc8f-432c-a0fd-ae8c92904e56-profile_image-300x300.png",
    "user_offline_image_url": "",
    "stream_id": 43976073036,
    "stream_game_id": "116747788",
    "stream_game_name": "Pools, Hot Tubs, and Beaches",
    "stream_title": "Hot Girl Bikini Contest",
    "stream_viewer_count": 32,
    "stream_thumbnail_url": "https://static-cdn.jtvnw.net/previews-ttv/live_user_yntmoe-{width}x{height}.jpg"
  },
  {
    "user_id": 403058230,
    "user_login": "sandra_owl",
    "user_display_name": "Sandra_Owl",
    "user_broadcaster_type": "affiliate",
    "user_profile_image_url": "https://static-cdn.jtvnw.net/jtv_user_pictures/56061104-84df-4f7a-8530-b240ba4161f7-profile_image-300x300.png",
    "user_offline_image_url": "https://static-cdn.jtvnw.net/jtv_user_pictures/20e8baa8-e8fc-42fb-bd16-2002700215b5-channel_offline_image-1920x1080.png",
    "stream_id": 40296282235,
    "stream_game_id": "509658",
    "stream_game_name": "Just Chatting",
    "stream_title": "!insta !socials 🖤ВЕРНУЛАСЬ ДОМОЙ🤍",
    "stream_viewer_count": 30,
    "stream_thumbnail_url": "https://static-cdn.jtvnw.net/previews-ttv/live_user_sandra_owl-{width}x{height}.jpg"
  },
  {
    "user_id": 121602102,
    "user_login": "stellarztv",
    "user_display_name": "StellarzTV",
    "user_broadcaster_type": "affiliate",
    "user_profile_image_url": "https://static-cdn.jtvnw.net/jtv_user_pictures/cc696361-729c-45a2-9f9b-a3a42129a8b0-profile_image-300x300.jpeg",
    "user_offline_image_url": "https://static-cdn.jtvnw.net/jtv_user_pictures/825adccc-9b86-43a9-af6e-642fbd8f6f14-channel_offline_image-1920x1080.png",
    "stream_id": 43982938588,
    "stream_game_id": "460630",
    "stream_game_name": "Tom Clancy's Rainbow Six Siege",
    "stream_title": "(UK/Latina) YOO HO HO ",
    "stream_viewer_count": 22,
    "stream_thumbnail_url": "https://static-cdn.jtvnw.net/previews-ttv/live_user_stellarztv-{width}x{height}.jpg"
  }
]
